bedrock_anthropic/__init__.py
bedrock_anthropic/async_client.py
bedrock_anthropic/client.py
bedrock_anthropic-0.0.5.dist-info/LICENSE
bedrock_anthropic-0.0.5.dist-info/METADATA
bedrock_anthropic-0.0.5.dist-info/WHEEL
bedrock_anthropic-0.0.5.dist-info/top_level.txt
bedrock_anthropic-0.0.5.dist-info/RECORD
