Metadata-Version: 2.1
Name: bedrock_anthropic
Version: 0.0.5
Summary: Client library for the anthropic API with the AWS Bedrock endpoint.
Author-email: Mustafa Aljadery <aljadery@usc.edu>, Siddharth Sharma <sidshr@stanford.edu>
License: Copyright 2023 Mustafa Aljadery, Siddharth Sharma.
Project-URL: Homepage, https://github.com/mustafaaljadery/anthropic-bedrock
Project-URL: Repository, https://github.com/mustafaaljadery/anthropic-bedrock
Keywords: Anthropic,LLM,Bedrock,Claude,OpenAI,tiktoken,AWS Bedrock
Classifier: Development Status :: 3 - Alpha
Classifier: Operating System :: OS Independent
Classifier: License :: OSI Approved :: MIT License
Classifier: Programming Language :: Python :: 3
Requires-Python: >=3.7
License-File: LICENSE
Requires-Dist: tokenizers
Requires-Dist: boto3
Requires-Dist: pathlib
Requires-Dist: typing
Requires-Dist: asyncio
